nessvec/2024-01-09-SAN-LAX-CPH-WAW-RZE-Ukraine-Scandinavian-AirPriceline-priceline-3YBBK7.md
nessvec/__init__.py
nessvec/benchmarking.py
nessvec/clean_wiktionary_titles.py
nessvec/constants.py
nessvec/crawler-filterlinks.py
nessvec/crawler.py
nessvec/data/constants/LANG_INFO.csv
nessvec/data/constants/LANG_ISO.csv
nessvec/data/constants/__init__.py
nessvec/data/constants/tlds-from-iana.csv
nessvec/data/constants/uri-schemes.xhtml.csv
nessvec/django_project/asgi.py
nessvec/django_project/settings.py
nessvec/django_project/urls.py
nessvec/django_project/wsgi.py
nessvec/examples/2022-01-15-SDML-mixed-precision-optimizers-relu-selu-elu-activation.md
nessvec/examples/2022-03-30-mob-programming-after-party-ch06-extreme-summarization-closest-stopword.hist.py
nessvec/examples/2022-03-30-mob-programming-after-party-ch06-extreme-summarization-closest-stopword.hist.py.md
nessvec/examples/2022-03-30-mob-programming-ch06-extreme-summarization.hist.py
nessvec/examples/ch06/.ipynb_checkpoints/pytorch_word2vec_wikitext2-checkpoint.ipynb
nessvec/examples/ch06/ch06_nessvectors.py
nessvec/examples/ch06/ch06_nessvectors_with_spacy.py
nessvec/examples/ch06/nessvectors.py
nessvec/examples/clean_ipy.sh
nessvec/examples/np_memmap_test_120GB.hist.ipy
nessvec/examples/tbd/etl_pocket_bookmarks_brian_piercey-edited.ipy
nessvec/examples/tbd/etl_pocket_bookmarks_brian_piercey-edited.py
nessvec/examples/tbd/etl_pocket_bookmarks_brian_piercey.py
nessvec/examples/wikipedia_crawl.hist.py
nessvec/fasttext.py
nessvec/files.py
nessvec/glove.py
nessvec/hist/datatable_word_vector_similarity.hist.ipy
nessvec/hist/glove_dataframe_to_hdf5.hist.py
nessvec/hist/pynn_index_king_queen.hist.ipy
nessvec/hist/vec_to_hdf5.hist.py
nessvec/hypervec.py
nessvec/indexers.py
nessvec/nessvectors.py
nessvec/re_patterns.py
nessvec/scripts/test_memory_usage.py
nessvec/spacy_language_model.py
nessvec/spell.py
nessvec/text.py
nessvec/translation.py
nessvec/util.py
nessvec/wikicrawl.py
nessvec/wip/ch02_sentiment.py
nessvec-0.2.0.dist-info/LICENSE.txt
nessvec-0.2.0.dist-info/METADATA
nessvec-0.2.0.dist-info/WHEEL
nessvec-0.2.0.dist-info/RECORD
