Metadata-Version: 2.3
Name: nessvec
Version: 0.2.0
Summary: Word embeddings with meaningful dimensions for better explainability.
License: GPLv3
Keywords: NLP,Natural Language Processing,Virtual Assistant,chatbot,Text Processing,Machine Learning,Text Mining,Deep Learning
Author: Hobson Lane
Author-email: hobson@tangibleai.com
Requires-Python: >=3.9
Classifier: Development Status :: 5 - Production/Stable
Classifier: Intended Audience :: Developers
Classifier: License :: Other/Proprietary License
Classifier: Operating System :: OS Independent
Classifier: Programming Language :: Python :: 3
Classifier: Programming Language :: Python :: 3.9
Classifier: Programming Language :: Python :: 3.10
Classifier: Programming Language :: Python :: 3.11
Classifier: Programming Language :: Python :: 3.12
Classifier: Programming Language :: Python :: 3.13
Classifier: Topic :: Software Development :: Libraries :: Python Modules
Classifier: Topic :: Text Processing :: Linguistic
Requires-Dist: beautifulsoup4 (>=4.12,<5.0)
Requires-Dist: dask
Requires-Dist: datatable
Requires-Dist: django (>=4.2.4,<5.0.0)
Requires-Dist: edit-distance (>=1.0.6,<2.0.0)
Requires-Dist: h5py (>=3.9.0,<4.0.0)
Requires-Dist: jsonschema (>=4.10.0,<4.18.0)
Requires-Dist: jupyter (==1.0.0)
Requires-Dist: meilisearch (>=0.28.2,<0.29.0)
Requires-Dist: nlpia2-wikipedia (>=1.5.14,<2.0.0)
Requires-Dist: pandas (>=2.1.4,<3.0.0)
Requires-Dist: pyarrow
Requires-Dist: pynndescent
Requires-Dist: python-dotenv (>=1.0.0,<2.0.0)
Requires-Dist: seaborn (>=0.13.0,<0.14.0)
Requires-Dist: sentence-transformers (>=2.2.2)
Requires-Dist: spacy
Requires-Dist: xmltodict (>=0.13.0,<0.14.0)
Project-URL: Documentation, https://gitlab.com/tangibleai/nessvec
Project-URL: Homepage, https://gitlab.com/tangibleai/nessvec
